prismic/__init__.py
prismic/base.py
prismic/document.py
prismic/ref.py
prismic_api-0.1.3.dist-info/DESCRIPTION.rst
prismic_api-0.1.3.dist-info/METADATA
prismic_api-0.1.3.dist-info/RECORD
prismic_api-0.1.3.dist-info/WHEEL
prismic_api-0.1.3.dist-info/metadata.json
prismic_api-0.1.3.dist-info/top_level.txt
